setup.py
CodeViking.Collections.egg-info/PKG-INFO
CodeViking.Collections.egg-info/SOURCES.txt
CodeViking.Collections.egg-info/dependency_links.txt
CodeViking.Collections.egg-info/namespace_packages.txt
CodeViking.Collections.egg-info/top_level.txt
codeviking/__init__.py
codeviking/collections/__init__.py
codeviking/collections/dict/_FrozenDict.py
codeviking/collections/dict/__init__.py
codeviking/collections/dict/_dictchain.py
codeviking/collections/dict/_dirdict.py
codeviking/collections/dict/_filedict.py
codeviking/collections/dict/_multidict.py
test/test__dict.py