Metadata-Version: 1.0
Name: CodeViking.Collections
Version: 0.10
Summary: Data collection objects
Home-page: http://hg.codeviking.com/collections/
Author: Dan Bullok
Author-email: opensource@codeviking.com
License: GNU GPLv3
Platform: any
Classifier: Development Status :: 3 - Alpha
Classifier: Intended Audience :: Developers
Classifier: License :: OSI Approved :: GNU General Public License (GPL)
Classifier: Natural Language :: English
Classifier: Operating System :: OS Independent
Classifier: Programming Language :: Python
Classifier: Topic :: Software Development :: Libraries :: Python Modules
